comtrade_pysharp/FileReader.dll
comtrade_pysharp/__init__.py
comtrade_pysharp/comtrade_pysharp.py
comtrade_pysharp-0.0.3.dist-info/METADATA
comtrade_pysharp-0.0.3.dist-info/WHEEL
comtrade_pysharp-0.0.3.dist-info/top_level.txt
comtrade_pysharp-0.0.3.dist-info/RECORD
