Metadata-Version: 2.1
Name: comtrade_pysharp
Version: 0.0.3
Summary: Simple reader for COMTRADE files, using C# underneath to be fast
Requires-Python: >=3.9
Requires-Dist: numpy
Requires-Dist: pythonnet
